{"cameraMode":{"drawMode":0,"name":"Shaded","section":"Shading Mode"},"sceneLighting":false,"audioPlay":false,"sceneViewState":{"m_AlwaysRefresh":false,"showFog":true,"showSkybox":false,"showFlares":true,"showImageEffects":true,"showParticleSystems":true,"showVisualEffectGraphs":true,"m_FxEnabled":true},"in2DMode":false,"pivot":{"x":-0.0025831907987594606,"y":-0.19240400195121766,"z":-0.01664796471595764},"rotation":{"x":0.33395716547966006,"y":0.31479182839393618,"z":-0.1191043108701706,"w":0.8805825710296631},"size":0.2640179693698883,"orthographic":false}